clickhouse_backend/__init__.py
clickhouse_backend/compat.py
clickhouse_backend/validators.py
clickhouse_backend/backend/__init__.py
clickhouse_backend/backend/base.py
clickhouse_backend/backend/client.py
clickhouse_backend/backend/creation.py
clickhouse_backend/backend/features.py
clickhouse_backend/backend/introspection.py
clickhouse_backend/backend/operations.py
clickhouse_backend/backend/schema.py
clickhouse_backend/driver/__init__.py
clickhouse_backend/driver/client.py
clickhouse_backend/driver/connection.py
clickhouse_backend/driver/escape.py
clickhouse_backend/driver/pool.py
clickhouse_backend/driver/types.py
clickhouse_backend/idworker/__init__.py
clickhouse_backend/idworker/base.py
clickhouse_backend/idworker/snowflake.py
clickhouse_backend/management/__init__.py
clickhouse_backend/management/commands/__init__.py
clickhouse_backend/management/commands/inspectdb.py
clickhouse_backend/models/__init__.py
clickhouse_backend/models/aggregates.py
clickhouse_backend/models/base.py
clickhouse_backend/models/engines.py
clickhouse_backend/models/indexes.py
clickhouse_backend/models/query.py
clickhouse_backend/models/fields/__init__.py
clickhouse_backend/models/fields/array.py
clickhouse_backend/models/fields/base.py
clickhouse_backend/models/fields/integer.py
clickhouse_backend/models/fields/json.py
clickhouse_backend/models/fields/map.py
clickhouse_backend/models/fields/tuple.py
clickhouse_backend/models/fields/utils.py
clickhouse_backend/models/functions/__init__.py
clickhouse_backend/models/functions/base.py
clickhouse_backend/models/functions/datetime.py
clickhouse_backend/models/functions/hashes.py
clickhouse_backend/models/functions/other.py
clickhouse_backend/models/functions/random.py
clickhouse_backend/models/functions/tuples.py
clickhouse_backend/models/sql/__init__.py
clickhouse_backend/models/sql/compiler.py
clickhouse_backend/models/sql/query.py
clickhouse_backend/patch/__init__.py
clickhouse_backend/patch/functions.py
django_clickhouse_backend-1.4.dist-info/licenses/LICENSE
django_clickhouse_backend-1.4.dist-info/METADATA
django_clickhouse_backend-1.4.dist-info/WHEEL
django_clickhouse_backend-1.4.dist-info/top_level.txt
django_clickhouse_backend-1.4.dist-info/RECORD
