Metadata-Version: 2.4
Name: django-clickhouse-backend
Version: 1.4
Summary: Django clickHouse database backend
Author-email: Lin Zhiwen <zhiwenlin1116@gmail.com>
License: MIT
Project-URL: Homepage, https://github.com/jayvynl/django-clickhouse-backend
Keywords: Django,ClickHouse,database,backend,engine,driver
Classifier: Framework :: Django
Classifier: Framework :: Django :: 3.2
Classifier: Framework :: Django :: 4
Classifier: Framework :: Django :: 4.0
Classifier: Framework :: Django :: 4.1
Classifier: Framework :: Django :: 4.2
Classifier: Framework :: Django :: 5
Classifier: Framework :: Django :: 5.0
Classifier: Framework :: Django :: 5.1
Classifier: Framework :: Django :: 5.2
Classifier: Intended Audience :: Developers
Classifier: License :: OSI Approved :: MIT License
Classifier: Programming Language :: Python
Classifier: Programming Language :: Python :: 3
Classifier: Programming Language :: Python :: 3 :: Only
Classifier: Programming Language :: Python :: 3.7
Classifier: Programming Language :: Python :: 3.8
Classifier: Programming Language :: Python :: 3.9
Classifier: Programming Language :: Python :: 3.10
Classifier: Programming Language :: Python :: 3.11
Classifier: Programming Language :: Python :: 3.12
Classifier: Programming Language :: Python :: 3.13
Requires-Python: <4,>=3.7
License-File: LICENSE
Requires-Dist: django>=3.2
Requires-Dist: clickhouse-driver==0.2.9
Dynamic: license-file
